pyastyle.pyd
pyastyle-1.1.5.dist-info/DESCRIPTION.rst
pyastyle-1.1.5.dist-info/METADATA
pyastyle-1.1.5.dist-info/metadata.json
pyastyle-1.1.5.dist-info/RECORD
pyastyle-1.1.5.dist-info/top_level.txt
pyastyle-1.1.5.dist-info/WHEEL
